TOPSIS-Utkarsh-101803613/__init__.py
TOPSIS-Utkarsh-101803613/topsis.py
TOPSIS_Utkarsh_101803613/__init__.py
TOPSIS_Utkarsh_101803613/topsis.py
TOPSIS_Utkarsh_101803613-0.2.dist-info/LICENSE.txt
TOPSIS_Utkarsh_101803613-0.2.dist-info/METADATA
TOPSIS_Utkarsh_101803613-0.2.dist-info/WHEEL
TOPSIS_Utkarsh_101803613-0.2.dist-info/top_level.txt
TOPSIS_Utkarsh_101803613-0.2.dist-info/RECORD
