Metadata-Version: 2.1
Name: TOPSIS-Utkarsh-101803613
Version: 0.2
Summary: A python package for Multiple Criteria Decision Making (MCDM) using Topsis
Home-page: https://github.com/utkarsh-1106/TOPSIS-Utkarsh-101803613
Author: Utkarsh Sinha
Author-email: utkarsh.sinha116@gmail.com
License: MIT
Keywords: TOPSIS,101803613,Utkarsh,TOPSIS-Utkarsh-101803613
Platform: UNKNOWN
Classifier: Development Status :: 3 - Alpha
Classifier: Intended Audience :: Developers
Classifier: Topic :: Software Development :: Build Tools
Classifier: License :: OSI Approved :: MIT License
Classifier: Programming Language :: Python :: 3
Classifier: Programming Language :: Python :: 3.4
Classifier: Programming Language :: Python :: 3.5
Classifier: Programming Language :: Python :: 3.6
Classifier: Programming Language :: Python :: 3.7
Classifier: Programming Language :: Python :: 3.8
Requires-Dist: pandas
